{
  "id": "63-16",
  "phase": "63",
  "status": "planned",
  "goal": "Audit REQUIREMENTS.xml canonical status — is it still the official planning artifact, or has that role moved to specs/ and context-frameworks/? Decision 2026-04-20 D5 follow-up.",
  "type": "design",
  "keywords": "",
  "depends": [],
  "commands": [],
  "files": [],
  "agent_id": "",
  "agent_role": "",
  "runtime": "",
  "model_profile": "",
  "resolved_model": "",
  "skill": "",
  "claimed": false,
  "claimed_at": "",
  "lease_expires_at": "",
  "resolution": "",
  "created_at": "2026-04-23T00:48:01.720Z",
  "updated_at": "2026-04-23T00:48:01.720Z"
}